[
  {
    "ParameterKey": "Environment",
    "ParameterValue": "Live"
  },
  {
      "ParameterKey": "RepositoryCodeCommit",
      "ParameterValue": ""
  },
  {
      "ParameterKey": "Branch",
      "ParameterValue": "master"
  },
  {
    "ParameterKey": "ProjectName",
    "ParameterValue": ""
  },
  {
    "ParameterKey": "S3Bucket",
    "ParameterValue": ""
  },
  {
    "ParameterKey": "CMKARN",
    "ParameterValue": ""
  },
  {
    "ParameterKey": "BeansTalkAppName",
    "ParameterValue": ""
  },
  {
    "ParameterKey": "BeansTalkEnvName",
    "ParameterValue": ""
  },
  {
    "ParameterKey": "CrossAccountCondition",
    "ParameterValue": "false"    
  },
  {
    "ParameterKey": "DevAccount",
    "ParameterValue": ""
  },
  {
    "ParameterKey": "DeploymentAccount",
    "ParameterValue": ""
  }
]

